database_routing/__init__.py
django_database_routing-1.2.0.dist-info/LICENSE
django_database_routing-1.2.0.dist-info/METADATA
django_database_routing-1.2.0.dist-info/WHEEL
django_database_routing-1.2.0.dist-info/top_level.txt
django_database_routing-1.2.0.dist-info/RECORD
